ddba/__init__.py
ddba/app.py
ddba/command.py
ddba/core.py
ddba/frontend/404.html
ddba/frontend/android-chrome-192x192.png
ddba/frontend/android-chrome-512x512.png
ddba/frontend/apple-touch-icon.png
ddba/frontend/favicon-16x16.png
ddba/frontend/favicon-32x32.png
ddba/frontend/favicon.ico
ddba/frontend/index.html
ddba/frontend/index.txt
ddba/frontend/macos.png
ddba/frontend/prompts.json
ddba/frontend/robots.txt
ddba/frontend/serviceWorker.js
ddba/frontend/serviceWorkerRegister.js
ddba/frontend/site.webmanifest
ddba/frontend/_next/static/chunks/04b39fde-81a0ff4664eb4ee5.js
ddba/frontend/_next/static/chunks/main-925f6ea435120800.js
ddba/frontend/_next/static/chunks/main-app-7f34739bcdf9cb2b.js
ddba/frontend/_next/static/chunks/polyfills-78c92fac7aa8fdd8.js
ddba/frontend/_next/static/chunks/webpack-2427bf9b6a6c272f.js
ddba/frontend/_next/static/chunks/app/layout-3f9408166927f408.js
ddba/frontend/_next/static/chunks/app/page-e61a1005269e325b.js
ddba/frontend/_next/static/chunks/pages/_app-5fe7e9aee4115c83.js
ddba/frontend/_next/static/chunks/pages/_error-5abe2fc777c161a8.js
ddba/frontend/_next/static/css/1ecdfc2a488188d1.css
ddba/frontend/_next/static/css/45807bbfbf295d6d.css
ddba/frontend/_next/static/css/db8139f6ca0b2e02.css
ddba/frontend/_next/static/media/KaTeX_AMS-Regular.1608a09b.woff
ddba/frontend/_next/static/media/KaTeX_AMS-Regular.4aafdb68.ttf
ddba/frontend/_next/static/media/KaTeX_AMS-Regular.a79f1c31.woff2
ddba/frontend/_next/static/media/KaTeX_Caligraphic-Bold.b6770918.woff
ddba/frontend/_next/static/media/KaTeX_Caligraphic-Bold.cce5b8ec.ttf
ddba/frontend/_next/static/media/KaTeX_Caligraphic-Bold.ec17d132.woff2
ddba/frontend/_next/static/media/KaTeX_Caligraphic-Regular.07ef19e7.ttf
ddba/frontend/_next/static/media/KaTeX_Caligraphic-Regular.55fac258.woff2
ddba/frontend/_next/static/media/KaTeX_Caligraphic-Regular.dad44a7f.woff
ddba/frontend/_next/static/media/KaTeX_Fraktur-Bold.9f256b85.woff
ddba/frontend/_next/static/media/KaTeX_Fraktur-Bold.b18f59e1.ttf
ddba-0.0.1.dist-info/METADATA
ddba-0.0.1.dist-info/WHEEL
ddba-0.0.1.dist-info/entry_points.txt
ddba-0.0.1.dist-info/top_level.txt
ddba-0.0.1.dist-info/RECORD
