Metadata-Version: 2.1
Name: ddba
Version: 0.0.1
Summary: UNKNOWN
Home-page: UNKNOWN
Author: 
License: UNKNOWN
Platform: UNKNOWN
Requires-Python: >=3.6.0
Requires-Dist: Flask
Requires-Dist: openai
Requires-Dist: flask-cors
